csvtojsonify/__init__.py
csvtojsonify-1.3.0.dist-info/METADATA
csvtojsonify-1.3.0.dist-info/WHEEL
csvtojsonify-1.3.0.dist-info/entry_points.txt
csvtojsonify-1.3.0.dist-info/top_level.txt
csvtojsonify-1.3.0.dist-info/RECORD
