Metadata-Version: 2.1
Name: csvtojsonify
Version: 1.3.0
Summary: A tool to convert CSV files to JSON.
Home-page: https://github.com/sriramsreedhar/csvtojsonify
Author: Sriram Sreedhar
Author-email: sriramsreedhar003@gmail.com
Requires-Python: >=3.9.6
